eaface/__init__.py
eaface/face_recognition.py
stu/__init__.py
stu/settings.py
stu/urls.py
stu/wsgi.py
veriface-0.0.1.dist-info/METADATA
veriface-0.0.1.dist-info/WHEEL
veriface-0.0.1.dist-info/top_level.txt
veriface-0.0.1.dist-info/RECORD
