Metadata-Version: 2.1
Name: veriface
Version: 0.0.1
Summary: This project provides an easy way to recognize faces using AI
Home-page: https://github.com/sunjian-github/ezface
Author: han
Author-email: 3091002212@qq.com
